{
  "entries": [
    {
      "id": "cp-mpo7ms6u-4exxgazc",
      "sessionId": "s-mpo7mqji-9pv74lft",
      "createdAt": 1779895177014,
      "label": "你好",
      "messageCount": 2,
      "fileCount": 0,
      "totalBytes": 0
    },
    {
      "id": "cp-mpo7rpzh-2qr3a8o7",
      "sessionId": "s-mpo7mqji-9pv74lft",
      "createdAt": 1779895407437,
      "label": "你建议怎么选",
      "messageCount": 4,
      "fileCount": 0,
      "totalBytes": 0
    },
    {
      "id": "cp-mpo7xv4k-izf8qn6e",
      "sessionId": "s-mpo7mqji-9pv74lft",
      "createdAt": 1779895694036,
      "label": "代码托管平台已经改名字",
      "messageCount": 6,
      "fileCount": 0,
      "totalBytes": 0
    },
    {
      "id": "cp-mpo7z5b1-mia3g73f",
      "sessionId": "s-mpo7mqji-9pv74lft",
      "createdAt": 1779895753885,
      "label": "将本地源码推到平台",
      "messageCount": 17,
      "fileCount": 0,
      "totalBytes": 0
    }
  ]
}